fffw/__init__.py
fffw/scaler.py
fffw/analysis/__init__.py
fffw/analysis/base.py
fffw/analysis/ffprobe.py
fffw/analysis/mediainfo.py
fffw/encoding/__init__.py
fffw/encoding/codecs.py
fffw/encoding/complex.py
fffw/encoding/ffmpeg.py
fffw/encoding/ffprobe.py
fffw/encoding/filters.py
fffw/encoding/inputs.py
fffw/encoding/mixins.py
fffw/encoding/outputs.py
fffw/encoding/sources.py
fffw/encoding/vector.py
fffw/graph/__init__.py
fffw/graph/base.py
fffw/graph/meta.py
fffw/wrapper/__init__.py
fffw/wrapper/base.py
fffw/wrapper/helpers.py
fffw/wrapper/params.py
fffw-7.0.0.dist-info/LICENSE
fffw-7.0.0.dist-info/METADATA
fffw-7.0.0.dist-info/WHEEL
fffw-7.0.0.dist-info/top_level.txt
fffw-7.0.0.dist-info/RECORD
