Metadata-Version: 2.1
Name: fffw
Version: 7.0.0
Summary: FFMPEG wrapper
Author-email: Sergey Tikhonov <zimbler@gmail.com>
License: MIT
Project-URL: homepage, https://github.com/just-work/fffw
Project-URL: documentation, https://fffw.readthedocs.io/en/latest/
Project-URL: repository, https://github.com/just-work/fffw.git
Project-URL: issues, https://github.com/just-work/fffw/issues
Keywords: ffmpeg,wrapper
Classifier: Development Status :: 5 - Production/Stable
Classifier: Environment :: Console
Classifier: Operating System :: POSIX
Classifier: Programming Language :: Python :: 3.8
Classifier: Programming Language :: Python :: 3.9
Classifier: Programming Language :: Python :: 3.10
Classifier: Programming Language :: Python :: 3.11
Classifier: Programming Language :: Python :: 3.12
Classifier: Topic :: Multimedia :: Video :: Conversion
License-File: LICENSE
Requires-Dist: pymediainfo
